bufferer/__init__.py
bufferer/__main__.py
bufferer/_bufferer.py
bufferer/_log.py
bufferer/py.typed
bufferer-0.24.1.dist-info/licenses/LICENSE.md
bufferer-0.24.1.dist-info/WHEEL
bufferer-0.24.1.dist-info/entry_points.txt
bufferer-0.24.1.dist-info/METADATA
bufferer-0.24.1.dist-info/RECORD
